textract_io/__init__.py
textract_io/main.py
textract_io/prompts.py
textract_io-2025.12.21154549.dist-info/METADATA
textract_io-2025.12.21154549.dist-info/WHEEL
textract_io-2025.12.21154549.dist-info/top_level.txt
textract_io-2025.12.21154549.dist-info/RECORD
