Metadata-Version: 2.4
Name: textract-io
Version: 2025.12.21154549
Summary: A new package designed to facilitate structured extraction of key information from scientific or factual text inputs, enabling precise summaries, data extraction, or categorization based on user promp
Author-email: textract-io <hi@eugene.plus>
License: MIT
Project-URL: Homepage, https://github.com/chigwell/textract-io
Requires-Python: >=3.9
Requires-Dist: langchain-llm7>=0.0.0
Requires-Dist: llmatch-messages>=0.0.0
Requires-Dist: langchain-core>=0.3.0
